midistuff/__init__.py
midistuff/controller.py
midistuff/error.py
midistuff/launchpad/base.py
midistuff/launchpad/enums.py
midistuff/launchpad/mk2.py
midistuff-0.0.2.dist-info/METADATA
midistuff-0.0.2.dist-info/WHEEL
midistuff-0.0.2.dist-info/top_level.txt
midistuff-0.0.2.dist-info/RECORD
